Metadata-Version: 2.1
Name: matrix-parse
Version: 0.0.1
Summary: Parse matrix by url
Home-page: 
Author: Ilia Artnaiev
Author-email: ilya.artnaev@gmail.com
License: MIT
Keywords: parse matrix
Classifier: Development Status :: 5 - Production/Stable
Classifier: License :: OSI Approved :: MIT License
Classifier: Programming Language :: Python :: 3
License-File: LICENSE.txt
